qcml_logging/__init__.py
qcml_logging/context.py
qcml_logging/formatters.py
qcml_logging/handlers.py
qcml_logging/logging_setup.py
qcml_logging-0.1.0.dist-info/LICENSE
qcml_logging-0.1.0.dist-info/METADATA
qcml_logging-0.1.0.dist-info/WHEEL
qcml_logging-0.1.0.dist-info/top_level.txt
qcml_logging-0.1.0.dist-info/RECORD
