Metadata-Version: 2.1
Name: qcml-logging
Version: 0.1.0
Summary: A Python library for advanced logging with support for multiple outputs and optional Slack integration.
Home-page: https://github.com/albertnieto/qcml-logging
Author: Albert Nieto
Author-email: Albert Nieto <nietom.albert@gmail.com>
License: Apache-2.0
Project-URL: Homepage, https://github.com/albertnieto/qcml-logging
Classifier: Programming Language :: Python :: 3
Classifier: License :: OSI Approved :: Apache Software License
Classifier: Operating System :: OS Independent
Requires-Python: >=3.6
License-File: LICENSE
Provides-Extra: slack
Requires-Dist: slack-sdk>=3.0.0; extra == "slack"
